{"id":"Zq7UnE9Bcs3jqQvwzCJNm","title":"STEPTREND_UP","desc":"","updated":1644116049466,"created":1644115080141,"custom":{},"fname":"ind.steptrend.STEPTREND_UP","type":"note","vault":{"fsPath":"jchartupdates","remote":{"type":"git","url":"git@github.com-ju:jchartupdates/jchartupdates.github.io.git"},"name":"jchartupdates"},"contentHash":"d15c47d54f24c525e397c49187d04221","links":[{"type":"wiki","from":{"fname":"ind.steptrend.STEPTREND_UP","id":"Zq7UnE9Bcs3jqQvwzCJNm","vaultName":"jchart"},"value":"ind.steptrend","alias":"ind.steptrend","position":{"start":{"line":10,"column":1,"offset":92},"end":{"line":10,"column":18,"offset":109},"indent":[]},"xvault":false,"sameFile":false,"to":{"fname":"ind.steptrend"}},{"from":{"fname":"ind.steptrend","vaultName":"jchartupdates"},"type":"backlink","position":{"start":{"line":3,"column":1,"offset":380},"end":{"line":3,"column":32,"offset":411},"indent":[]},"value":"ind.steptrend.STEPTREND_UP"},{"from":{"fname":"daily.journal.2022.02.05","vaultName":"jchartupdates"},"type":"backlink","position":{"start":{"line":10,"column":1,"offset":77},"end":{"line":10,"column":32,"offset":108},"indent":[]},"value":"ind.steptrend.STEPTREND_UP"},{"from":{"fname":"daily.journal.2022.02.07","vaultName":"jchartupdates"},"type":"backlink","position":{"start":{"line":10,"column":1,"offset":77},"end":{"line":10,"column":32,"offset":108},"indent":[]},"value":"ind.steptrend.STEPTREND_UP"},{"from":{"fname":"daily.journal.2022.02.08","vaultName":"jchartupdates"},"type":"backlink","position":{"start":{"line":10,"column":1,"offset":77},"end":{"line":10,"column":32,"offset":108},"indent":[]},"value":"ind.steptrend.STEPTREND_UP"},{"from":{"fname":"daily.journal.2022.02.09","vaultName":"jchartupdates"},"type":"backlink","position":{"start":{"line":11,"column":1,"offset":107},"end":{"line":11,"column":32,"offset":138},"indent":[]},"value":"ind.steptrend.STEPTREND_UP"},{"from":{"fname":"daily.journal.2022.03.05","vaultName":"jchartupdates"},"type":"backlink","position":{"start":{"line":15,"column":1,"offset":203},"end":{"line":15,"column":32,"offset":234},"indent":[]},"value":"ind.steptrend.STEPTREND_UP"}],"anchors":{"price-moved-to-a-7-day-high":{"type":"header","text":"Price Moved to a 7 Day High","value":"price-moved-to-a-7-day-high","line":8,"column":2,"depth":3}},"children":[],"parent":"nMF7DHiNJFyLgEyPq9Ddx","data":{}}
